config
trellogd
