Metadata-Version: 1.1
Name: trellogd
Version: 0.2.3
Summary: A tool for organizing your jobsearch
Home-page: https://github.com/kmix27/trello_glassdoor
Author: Kyle Mix
Author-email: kyle@kylemix.com
License: MIT
Keywords: job search glassdoor glass door trello organization
Platform: UNKNOWN
Classifier: Development Status :: 3 - Alpha
Classifier: License :: OSI Approved :: MIT License
Classifier: Programming Language :: Python :: 3.5
